pelican/plugins/photos/SourceCodePro-Bold.otf
pelican/plugins/photos/SourceCodePro-Regular.otf
pelican/plugins/photos/__init__.py
pelican/plugins/photos/licenses.json
pelican/plugins/photos/photos.py
pelican/plugins/photos/test_photos.py
pelican_photos-1.6.2.dist-info/METADATA
pelican_photos-1.6.2.dist-info/WHEEL
pelican_photos-1.6.2.dist-info/entry_points.txt
pelican_photos-1.6.2.dist-info/RECORD
