Metadata-Version: 2.1
Name: pelican-photos
Version: 1.6.2
Summary: Add a photo or a gallery of photos to an article
Keywords: pelican,plugin,photos,image
Author-Email: Joaquim Baptista <pxquim@gmail.com>
License: AGPL-3.0
Classifier: Development Status :: 5 - Production/Stable
Classifier: Environment :: Console
Classifier: Framework :: Pelican
Classifier: Framework :: Pelican :: Plugins
Classifier: Intended Audience :: End Users/Desktop
Classifier: Operating System :: OS Independent
Classifier: Programming Language :: Python :: 3
Classifier: Topic :: Internet :: WWW/HTTP
Classifier: Topic :: Software Development :: Libraries :: Python Modules
Project-URL: Funding, https://donate.getpelican.com/
Project-URL: Issue Tracker, https://github.com/pelican-plugins/photos/issues
Requires-Python: <4.0,>=3.8.1
Requires-Dist: pelican>=4.5
Requires-Dist: piexif~=1.1.3
Requires-Dist: Pillow<12.0.0,>=10.0.1
Provides-Extra: markdown
Requires-Dist: markdown; extra == "markdown"
